{"symbol": "133LM4", "market": "Nano Bitcoin Perp Style", "navn_no": "Bitcoin Mini Perp", "kategori": "krypto", "report": "tff", "weeks": 25, "data": [{"date": "2025-07-22", "spec_net": -974, "spec_long": 0, "spec_short": 974, "oi": 9722}, {"date": "2025-07-29", "spec_net": -11175, "spec_long": 2069, "spec_short": 13244, "oi": 21199}, {"date": "2025-08-05", "spec_net": -26760, "spec_long": 458, "spec_short": 27218, "oi": 31941}, {"date": "2025-08-12", "spec_net": -16677, "spec_long": 2098, "spec_short": 18775, "oi": 32794}, {"date": "2025-08-19", "spec_net": -18218, "spec_long": 3317, "spec_short": 21535, "oi": 37893}, {"date": "2025-08-26", "spec_net": -21815, "spec_long": 7591, "spec_short": 29406, "oi": 51853}, {"date": "2025-09-02", "spec_net": -13774, "spec_long": 10703, "spec_short": 24477, "oi": 52477}, {"date": "2025-09-09", "spec_net": -18781, "spec_long": 2806, "spec_short": 21587, "oi": 48750}, {"date": "2025-09-16", "spec_net": -13091, "spec_long": 7196, "spec_short": 20287, "oi": 54954}, {"date": "2025-09-23", "spec_net": -17534, "spec_long": 282, "spec_short": 17816, "oi": 48193}, {"date": "2025-09-30", "spec_net": -4544, "spec_long": 13571, "spec_short": 18115, "oi": 58044}, {"date": "2025-10-07", "spec_net": 8190, "spec_long": 26580, "spec_short": 18390, "oi": 69407}, {"date": "2025-10-14", "spec_net": -36551, "spec_long": 2053, "spec_short": 38604, "oi": 65879}, {"date": "2025-10-21", "spec_net": -11659, "spec_long": 8669, "spec_short": 20328, "oi": 66712}, {"date": "2025-10-28", "spec_net": -5326, "spec_long": 10534, "spec_short": 15860, "oi": 72796}, {"date": "2025-11-04", "spec_net": -19043, "spec_long": 2098, "spec_short": 21141, "oi": 83228}, {"date": "2025-11-10", "spec_net": -6046, "spec_long": 18878, "spec_short": 24924, "oi": 87789}, {"date": "2025-11-18", "spec_net": -60255, "spec_long": 3013, "spec_short": 63268, "oi": 108462}, {"date": "2025-11-25", "spec_net": -36372, "spec_long": 4770, "spec_short": 41142, "oi": 101538}, {"date": "2025-12-02", "spec_net": -9909, "spec_long": 29257, "spec_short": 39166, "oi": 115703}, {"date": "2025-12-09", "spec_net": -8837, "spec_long": 61171, "spec_short": 70008, "oi": 145711}, {"date": "2025-12-16", "spec_net": -22653, "spec_long": 28395, "spec_short": 51048, "oi": 127450}, {"date": "2025-12-23", "spec_net": 4800, "spec_long": 30806, "spec_short": 26006, "oi": 113519}, {"date": "2025-12-30", "spec_net": 2423, "spec_long": 40114, "spec_short": 37691, "oi": 122780}, {"date": "2026-03-17", "spec_net": 38889, "spec_long": 119114, "spec_short": 80225, "oi": 219022}]}